objectscale_s3_client/__init__.py
objectscale_s3_client/data/s3/2023-2-11/service-2.sdk-extras.json
objectscale_s3_client-1.0.0.dist-info/LICENSE
objectscale_s3_client-1.0.0.dist-info/METADATA
objectscale_s3_client-1.0.0.dist-info/NOTICE.md
objectscale_s3_client-1.0.0.dist-info/WHEEL
objectscale_s3_client-1.0.0.dist-info/top_level.txt
objectscale_s3_client-1.0.0.dist-info/RECORD
