Metadata-Version: 2.1
Name: objectscale-s3-client
Version: 1.0.0
Summary: Open-source S3 client library in python to support ObjectScales proprietary S3 extensions
Author: Drayer Sivertsen
Author-email: Drayer Sivertsen <drayer.sivertsen@wsu.edu>, Nathan Marugame <nathan.marugame@wsu.edu>, Killian Griffin <killian.griffin@wsu.edu>
Project-URL: Homepage, https://github.com/EMCECS/objectscale-s3-client-python
Keywords: ObjectScale,S3,Dell,boto3,botocore
Classifier: Development Status :: 3 - Alpha
Classifier: Intended Audience :: Developers
Classifier: License :: OSI Approved :: Apache Software License
Classifier: Natural Language :: English
Classifier: Programming Language :: Python :: 3.10
Classifier: Topic :: Software Development :: Libraries
License-File: LICENSE
License-File: NOTICE.md
Requires-Dist: boto3
Provides-Extra: dev
Requires-Dist: unittest ; extra == 'dev'
Requires-Dist: pytest ; extra == 'dev'
